README.md
setup.cfg
setup.py
eis/__init__.py
eis/partner/__init__.py
eis/partner/api_client.py
eis/partner/configuration.py
eis/partner/exceptions.py
eis/partner/model_utils.py
eis/partner/rest.py
eis/partner/api/__init__.py
eis/partner/api/default_api.py
eis/partner/api/partner_invitations_api.py
eis/partner/api/partner_relations_api.py
eis/partner/api/partner_tags_api.py
eis/partner/api/partner_types_api.py
eis/partner/api/partner_versions_api.py
eis/partner/api/partners_api.py
eis/partner/apis/__init__.py
eis/partner/model/__init__.py
eis/partner/model/create_or_update_partner_from_account_request_dto.py
eis/partner/model/create_or_update_partner_from_account_response_class.py
eis/partner/model/create_partner_relation_request_dto_rest.py
eis/partner/model/create_partner_relation_response_class.py
eis/partner/model/create_partner_request_dto.py
eis/partner/model/create_partner_response_class.py
eis/partner/model/create_partner_type_request_dto.py
eis/partner/model/create_partner_type_response_class.py
eis/partner/model/create_tag_request_dto.py
eis/partner/model/create_tag_response_class.py
eis/partner/model/delete_response_class.py
eis/partner/model/get_partner_relation_class.py
eis/partner/model/get_partner_relation_type_class.py
eis/partner/model/get_partner_response_class.py
eis/partner/model/get_partner_type_response_class.py
eis/partner/model/get_partner_version_response_class.py
eis/partner/model/get_tag_response_class.py
eis/partner/model/grouped_related_partners_class.py
eis/partner/model/inline_response200.py
eis/partner/model/inline_response503.py
eis/partner/model/invite_class.py
eis/partner/model/invite_partner_to_eis_request_dto.py
eis/partner/model/invite_partner_to_eis_response_class.py
eis/partner/model/list_partner_relation_class.py
eis/partner/model/list_partner_relation_types_class.py
eis/partner/model/list_partner_types_response_class.py
eis/partner/model/list_partner_versions_response_class.py
eis_partner.egg-info/PKG-INFO
eis_partner.egg-info/SOURCES.txt
eis_partner.egg-info/dependency_links.txt
eis_partner.egg-info/requires.txt
eis_partner.egg-info/top_level.txt
