Metadata-Version: 2.1
Name: eis-partner
Version: 1.18.0
Summary: EMIL PartnerService
Home-page: UNKNOWN
Author: Contact us
Author-email: kontakt@emil.de
License: UNKNOWN
Keywords: OpenAPI,OpenAPI-Generator,EMIL PartnerService
Platform: UNKNOWN
Requires-Python: >=3.6
